[
  {
    "product": "albumbuddy",
    "category": "홈",
    "pagePath": "/shop",
    "pageTitle": "AlbumBuddy 홈/샵 메인",
    "featureName": "홈/메인",
    "priority": "critical",
    "coverageStatus": "none",
    "source": "manual",
    "tag": "albumbuddy.home",
    "notes": "AB-HC-01, AB-PERF-01, AB-HC-03, AB-PAGE-01~03, AB-NAV-06~07",
    "displayOrder": 1
  },
  {
    "product": "albumbuddy",
    "category": "홈",
    "pagePath": "/shop",
    "pageTitle": "AlbumBuddy 홈/샵 메인",
    "featureName": "홈 콘텐츠 섹션",
    "priority": "high",
    "coverageStatus": "none",
    "source": "manual",
    "tag": "albumbuddy.home.sections",
    "notes": "AB-PAGE-04, AB-PAGE-05, AB-ACTION-01",
    "displayOrder": 2
  },
  {
    "product": "albumbuddy",
    "category": "검색",
    "pagePath": "/shop",
    "pageTitle": "검색 진입 오버레이/입력",
    "featureName": "검색 진입",
    "priority": "medium",
    "coverageStatus": "none",
    "source": "manual",
    "tag": "albumbuddy.search.entry",
    "notes": "AB-SEARCH-01",
    "displayOrder": 3
  },
  {
    "product": "albumbuddy",
    "category": "검색",
    "pagePath": "/search/result",
    "pageTitle": "검색 결과 페이지",
    "featureName": "검색 결과",
    "priority": "high",
    "coverageStatus": "none",
    "source": "manual",
    "tag": "albumbuddy.search.results",
    "notes": "AB-SEARCH-02, AB-SEARCH-03",
    "displayOrder": 4
  },
  {
    "product": "albumbuddy",
    "category": "서비스",
    "pagePath": "/about",
    "pageTitle": "About 페이지",
    "featureName": "About 페이지",
    "priority": "medium",
    "coverageStatus": "none",
    "source": "manual",
    "tag": "albumbuddy.about",
    "notes": "AB-HC-02, AB-NAV-01, AB-NAV-02, AB-PAGE-06, AB-NAV-06~07",
    "displayOrder": 5
  },
  {
    "product": "albumbuddy",
    "category": "서비스",
    "pagePath": "/pricing",
    "pageTitle": "Pricing 페이지",
    "featureName": "Pricing 페이지",
    "priority": "medium",
    "coverageStatus": "none",
    "source": "manual",
    "tag": "albumbuddy.pricing",
    "notes": "AB-HC-02, AB-NAV-03, AB-NAV-04, AB-PAGE-07, AB-NAV-06",
    "displayOrder": 6
  },
  {
    "product": "albumbuddy",
    "category": "상품",
    "pagePath": "/product/:id",
    "pageTitle": "상품 상세 페이지",
    "featureName": "상품 상세",
    "priority": "critical",
    "coverageStatus": "none",
    "source": "manual",
    "tag": "albumbuddy.product.detail",
    "notes": "AB-NAV-05, AB-PAGE-08, AB-DATA-01",
    "displayOrder": 7
  },
  {
    "product": "albumbuddy",
    "category": "상품",
    "pagePath": "/shop",
    "pageTitle": "Request item CTA",
    "featureName": "Request item",
    "priority": "high",
    "coverageStatus": "none",
    "source": "manual",
    "tag": "albumbuddy.request-item",
    "notes": "AB-ACTION-02, AB-ACTION-03",
    "displayOrder": 8
  },
  {
    "product": "albumbuddy",
    "category": "대시보드",
    "pagePath": "/dashboard/purchasing",
    "pageTitle": "대시보드 인증 진입",
    "featureName": "대시보드 인증 게이트",
    "priority": "high",
    "coverageStatus": "none",
    "source": "manual",
    "tag": "albumbuddy.dashboard.auth",
    "notes": "AB-AUTH-01, AB-AUTH-02, AB-AUTH-03",
    "displayOrder": 9
  },
  {
    "product": "albumbuddy",
    "category": "대시보드",
    "pagePath": "/dashboard/purchasing",
    "pageTitle": "My orders / Purchasing",
    "featureName": "구매 내역",
    "priority": "critical",
    "coverageStatus": "none",
    "source": "manual",
    "tag": "albumbuddy.dashboard.purchasing",
    "notes": "AB-PAGE-09, AB-PAGE-10, AB-PAGE-11",
    "displayOrder": 10
  },
  {
    "product": "albumbuddy",
    "category": "대시보드",
    "pagePath": "/dashboard/package",
    "pageTitle": "My packages / Package",
    "featureName": "패키지 내역",
    "priority": "high",
    "coverageStatus": "none",
    "source": "manual",
    "tag": "albumbuddy.dashboard.package",
    "notes": "AB-PAGE-12, AB-PAGE-13, AB-PAGE-14",
    "displayOrder": 11
  }
]
